{
  "users": [
    {
      "name": "فاطمه",
      "family": "نوری مطلق",
      "email": "fatemehnm1378@gmail.com",
      "password": "123456",
      "education": "کارشناسی",
      "eduPlace": "دانشگاه قم",
      "province": "قم",
      "city": "قم",
      "id": 1
    },
    {
      "name": "سارا",
      "family": "کریمی",
      "email": "karimi2019@gmail.com",
      "password": "789789",
      "education": "کارشناسی ارشد",
      "eduPlace": "دانشگاه قم",
      "province": "قم",
      "city": "قم",
      "id": 2
    },
    {
      "name": "سوفیا",
      "family": "عموئی",
      "email": "sofiaamoei@gmail.com",
      "password": "121212",
      "education": "کارشناسی",
      "eduPlace": "دانشگاه قم",
      "province": "قم",
      "city": "قم",
      "id": 3
    },
    {
      "name": "کوثر",
      "family": "شفاهی",
      "email": "kosarshafahi@gmail.com",
      "password": "454545",
      "education": "کارشناسی",
      "eduPlace": "دانشگاه قم",
      "province": "قم",
      "city": "قم",
      "id": 4
    },
    {
      "name": "علی",
      "family": "محبی",
      "email": "alimohebi@gmail.com",
      "password": "121212",
      "education": "کارشناسی ارشد",
      "eduPlace": "دانشگاه قم",
      "province": "تهران",
      "city": "تهران",
      "id": 5
    },
    {
      "name": "ساناز",
      "family": "بهرامی",
      "email": "sanaz@gmail.com",
      "password": "123123",
      "education": "کاردانی",
      "eduPlace": "دانشگاه ازاد",
      "province": "تهران",
      "city": "قدس",
      "id": 6
    }
  ]
}